lib/__init__.py
lib/lora_contol.py
lib/servo.py
lib/stepper_control-muwon-750XGK-safeBackup-0001.py
lib/stepper_control.py
lib/ultrasonic_sensor.py
rapycontrol-0.1.0.dist-info/licenses/LICENSE.txt
rapycontrol-0.1.0.dist-info/METADATA
rapycontrol-0.1.0.dist-info/WHEEL
rapycontrol-0.1.0.dist-info/top_level.txt
rapycontrol-0.1.0.dist-info/RECORD
