Metadata-Version: 2.4
Name: rapycontrol
Version: 0.1.0
Summary: A Python library for controlling stepper motors and other devices.
Home-page: https://github.com/lmwmason/rapycontrol/tree/main/rapycontrol
Author: Muwon Lee
Author-email: lmwmason@naver.com
Requires-Python: >=3.6
License-File: LICENSE.txt
Requires-Dist: RPi.GPIO==0.7.1
Requires-Dist: pyserial==3.5
Dynamic: author
Dynamic: author-email
Dynamic: description
Dynamic: description-content-type
Dynamic: home-page
Dynamic: license-file
Dynamic: requires-dist
Dynamic: requires-python
Dynamic: summary
